{
    "InheritFrom": "paragraph_base_style.json",
    "Default": {
        "FillTextureFramed": {
            "TextureId": "Textures/button_alternative.png",
            "ExternalSourceRect": {"X": 0, "Y": 0, "Width": 76, "Height": 24},
            "FrameWidth": {"X": 15, "Y": 8}
        },
        "TextAlignment": "Center",
        "Padding": {"Left": 12, "Right": 12, "Top": 8, "Bottom": 8},
        "DefaultWidth": {"Value": 100, "Unit": "Percents"}
    },
    "Targeted": {
        "FillTextureFramed": {
            "TextureId": "Textures/button_alternative_hover.png",
            "ExternalSourceRect": {"X": 0, "Y": 0, "Width": 76, "Height": 24},
            "FrameWidth": {"X": 15, "Y": 8}
        }
    },
    "Interacted": {
        "FillTextureFramed": {
            "TextureId": "Textures/button_alternative_down.png",
            "ExternalSourceRect": {"X": 0, "Y": 0, "Width": 76, "Height": 24},
            "FrameWidth": {"X": 15, "Y": 8}
        }
    },
    "Disabled": {"EffectIdentifier": "disabled"},
    "DefaultTextAnchor": "Center",
    "InterpolateStatesSpeed": 5
}
